geo_sampling/__init__.py
geo_sampling/geo_roads.py
geo_sampling/sample_roads.py
geo_sampling/utils.py
geo_sampling-0.2.2.dist-info/licenses/LICENSE
geo_sampling-0.2.2.dist-info/METADATA
geo_sampling-0.2.2.dist-info/WHEEL
geo_sampling-0.2.2.dist-info/entry_points.txt
geo_sampling-0.2.2.dist-info/top_level.txt
geo_sampling-0.2.2.dist-info/RECORD
