Metadata-Version: 2.4
Name: geo-sampling
Version: 0.2.2
Summary: Scripts for sampling Geo data sets by the specific region name
Author-email: Suriyan Laohaprapanon <suriyant@gmail.com>, Gaurav Sood <gsood07@gmail.com>
License-Expression: MIT
Project-URL: Homepage, https://github.com/geosensing/geo_sampling
Project-URL: Repository, https://github.com/geosensing/geo_sampling
Keywords: geo,street,road,openstreetmap,osm,city
Classifier: Development Status :: 4 - Beta
Classifier: Intended Audience :: Developers
Classifier: Programming Language :: Python :: 3.11
Classifier: Programming Language :: Python :: 3.12
Classifier: Topic :: Scientific/Engineering :: Information Analysis
Classifier: Topic :: Scientific/Engineering :: GIS
Classifier: Topic :: Scientific/Engineering :: Visualization
Classifier: Topic :: Software Development :: Libraries :: Python Modules
Requires-Python: >=3.10
License-File: LICENSE
Requires-Dist: pyshp>=2.3.1
Requires-Dist: matplotlib>=3.5.0
Requires-Dist: pyproj>=3.3.0
Requires-Dist: Shapely>=2.0.0
Requires-Dist: utm>=0.7.0
Requires-Dist: beautifulsoup4>=4.10.0
Requires-Dist: requests>=2.32.0
Provides-Extra: dev
Requires-Dist: check-manifest; extra == "dev"
Provides-Extra: test
Requires-Dist: coverage; extra == "test"
Requires-Dist: pytest; extra == "test"
Provides-Extra: docs
Requires-Dist: sphinx>=4.0; extra == "docs"
Requires-Dist: sphinx_rtd_theme; extra == "docs"
Requires-Dist: tomli>=1.2.0; python_version < "3.11" and extra == "docs"
Dynamic: license-file
